{
    "url": "https://www.geipi-polytech.org/formations/ingenieur-en-informatique-et-ingenierie-mathematique/",
    "site": "geipi-polytech.org",
    "category": "ingenieur-en-informatique-et-ingenierie-mathematique",
    "title": "Formation :Ingénieur en Informatique et ingénierie mathématique",
    "hash": "1ef1809c218894bd462206dbef069c496d7936ae8edacca3a328268fb683adb6",
    "last_modified": "2025-02-06T15:42:31+00:00",
    "scraped_at": "2025-06-18T08:45:00.840163+00:00",
    "content": "# Formation :Ingénieur en Informatique et ingénierie mathématique\n## Polytech Paris-Saclay\nPrésentation Située au cœur du Plateau de Saclay, Polytech Paris-Saclay bénéficie d’un environnement exceptionnel en matière de technologies, d’innovation et de recherche. L’école propose 4 spécialités habilitées par la Commission des Titres d’Ingénieurs : Polytech Paris-Saclay constitue une école dont le cursus, organisé sur 5 ans est entièrement tourné vers la formation au métier d’ingénieur. […]"
}