{
    "url": "https://www.polytech-reseau.org/category/alternance/",
    "site": "polytech-reseau.org",
    "category": "alternance",
    "title": "Alternance",
    "hash": "7a61b9ad07d479cf22fafc27f852b89a101f6bcb0fc4744529a4ffb853007fad",
    "last_modified": "2024-03-21T08:03:24+00:00",
    "scraped_at": "2025-06-18T08:41:51.425747+00:00",
    "content": "# Alternance\n## Comment l’IA influence le sport\nLilian Bergamaschi est élève ingénieur en 4e année en spécialité informatique et statistique à Polytech Lille. Il effectue son cycle ingénieur en apprentissage au Stade Rochelais. Il nous fait découvrir comment certaines données sont exploitées dans le rugby. « Il y a une cellule scientifique au sein du club pour l’accompagnementLire la suite…"
}